{
  "title": "الرئيسية",
  "subtitle": "بواسطة: FRONT EVILL",
  "tabs": {
    "main": "الرئيسية",
    "visuals": "المرئيات",
    "player": "اللاعب",
    "settings": "إعدادات السكربت",
    "donate": "تبرع"
  },
  "buttons": {
    "auto_win": "فوز تلقائي",
    "new_colors": "ألوان ESP جديدة (كل الخرائط)",
    "test_notification": "اختبار الإشعارات"
  },
  "toggles": {
    "overcoming": "تجاوز الصعوبات",
    "anti_afk": "منع AFK",
    "anti_seat": "منع الجلوس",
    "anti_slide": "منع الانزلاق",
    "esp_players": "ESP للاعبين",
    "detect_object": "كشف الكائن 38",
    "notifications": "تفعيل الإشعارات",
    "sound": "الصوت",
    "loop_sound": "تكرار الصوت",
    "auto_slap": "صفع تلقائي لجميع اللاعبين"
  },
  "sliders": {
    "duration": "المدة",
    "volume": "مستوى الصوت"
  },
  "sections": {
    "win_map": "خريطة الفوز",
    "anti": "منع",
    "esp": "ESP",
    "last": "الأخير",
    "notify": "إشعار",
    "slap": "الصفع التلقائي"
  },
  "notifications": {
    "success": "نجاح!",
    "discord_copy": "تم نسخ سيرفر ديسكورد"
  }
}
