{
  "title": "मुख्य",
  "subtitle": "द्वारा: FRONT EVILL",
  "tabs": {
    "main": "मुख्य",
    "targeting": "लक्ष्य साधना",
    "visuals": "दृश्य",
    "player": "खिलाड़ी",
    "settings": "स्क्रिप्ट सेटिंग्स",
    "donate": "दान करें"
  },
  "buttons": {
    "auto_win": "स्वचालित जीत",
    "new_colors": "नई ESP रंग (सभी मानचित्र)",
    "test_notification": "सूचना परीक्षण",
    "choose_player_tool": "खिलाड़ी उपकरण चुनें",
    "teleport_to_target": "लक्ष्य पर टेलीपोर्ट"
  },
  "toggles": {
    "overcoming": "मुश्किलों पर काबू पाएं",
    "anti_afk": "एंटी एएफके",
    "anti_seat": "एंटी सीट",
    "anti_slide": "एंटी-स्लाइड",
    "esp_players": "ESP खिलाड़ी",
    "detect_object": "ESP जीत",
    "notifications": "सूचनाएँ सक्रिय करें",
    "sound": "ध्वनि",
    "loop_sound": "ध्वनि दोहराएं",
    "auto_slap": "स्वचालित सभी खिलाड़ियों को थप्पड़",
    "camera_follow": "कैमरा लक्ष्य पर अनुसरण",
    "slap_target": "लक्ष्य को थप्पड़"
  },
  "sliders": {
    "duration": "अवधि",
    "volume": "ध्वनि स्तर"
  },
  "sections": {
    "win_map": "जीत का नक्शा",
    "anti": "एंटी",
    "esp": "ESP",
    "last": "अंतिम",
    "notify": "सूचित करें",
    "slap": "स्वचालित थप्पड़"
  },
  "notifications": {
    "success": "सफल!",
    "discord_copy": "डिस्कॉर्ड सर्वर कॉपी किया गया"
  },
  "input": {
    "player_targeting": "खिलाड़ियों को लक्षित करना"
  }
}
